{
  "kind": "coverage_report",
  "version": "1.0",
  "generatedAt": "2026-02-12T06:30:19.833Z",
  "sources": {
    "buildRequest": true,
    "implementationPlan": true
  },
  "requirements": {
    "total": 2,
    "implemented": 2,
    "items": [
      {
        "id": "REQ-1",
        "summary": "Update the HUD tab bar so all tabs are reachable on small screens by reducing each tab’s visual width and supporting horizontal overflow scrolling (e.g., when the full tab set exceeds viewport width).",
        "status": "implemented",
        "plannedFiles": [
          "frontend/src/components/hud/HudTabsBar.tsx",
          "frontend/src/index.css"
        ],
        "matchedFiles": [
          "frontend/src/index.css"
        ]
      },
      {
        "id": "REQ-2",
        "summary": "Add a compact rendering mode for `HudTabsBar` that, at small widths, shows only the tab name (label) and removes/reduces secondary micro-text so each tab consumes less space while remaining readable.",
        "status": "implemented",
        "plannedFiles": [
          "frontend/src/components/hud/HudTabsBar.tsx",
          "frontend/src/index.css"
        ],
        "matchedFiles": [
          "frontend/src/index.css"
        ]
      }
    ]
  },
  "changedFiles": [
    "build-request.json",
    "feature_evidence.json",
    "frontend-file-summaries.txt",
    "frontend-implementation-plan.json",
    "frontend/src/index.css",
    "project_state.json",
    "scratch/component-selection.json",
    "spec.md",
    "spec_vs_diff_report.json"
  ]
}